riemann_keys/__init__.py
riemann_keys/base58.py
riemann_keys/bip39.py
riemann_keys/hdkey.py
riemann_keys/utils.py
riemann_keys/data/__init__.py
riemann_keys/data/english.py
riemann_keys/tests/__init__.py
riemann_keys/tests/bip39_test_vectors.py
riemann_keys/tests/test_bip39.py
riemann_keys/tests/test_hdkey.py
riemann_keys-0.1.2.dist-info/LICENSE
riemann_keys-0.1.2.dist-info/METADATA
riemann_keys-0.1.2.dist-info/WHEEL
riemann_keys-0.1.2.dist-info/top_level.txt
riemann_keys-0.1.2.dist-info/RECORD
