Metadata-Version: 2.1
Name: riemann-keys
Version: 0.1.2
Summary: Hierarchical deterministic wallet creation tool
Home-page: UNKNOWN
Author: ['Harsha Goli', 'James Prestwich', 'RJ Rybarczyk', 'Jarrett Wheatley']
Author-email: UNKNOWN
License: LGPLv3.0
Keywords: bitcoin ethereum keys bip32 bip39 bip44
Platform: UNKNOWN
Requires-Dist: riemann-secpy256k1 (==0.2.8)
